minivectordb/__init__.py
minivectordb/embedding_model.py
minivectordb/sharded_vector_database.py
minivectordb/sharded_vector_database_usearch.py
minivectordb/vector_database.py
minivectordb/resources/embedding_model_quantized.onnx
minivectordb_simple-1.1.0.dist-info/licenses/LICENSE
tests/__init__.py
tests/test_embedding_model.py
tests/test_mongolike_operators.py
tests/test_multithreaded_operations.py
tests/test_sharded_mongolike_operators.py
tests/test_sharded_multithreaded_operations.py
tests/test_sharded_vector_database.py
tests/test_sharded_vector_database_usearch.py
tests/test_vector_database.py
minivectordb_simple-1.1.0.dist-info/METADATA
minivectordb_simple-1.1.0.dist-info/WHEEL
minivectordb_simple-1.1.0.dist-info/top_level.txt
minivectordb_simple-1.1.0.dist-info/RECORD
