Metadata-Version: 2.4
Name: minivectordb_simple
Version: 1.1.0
Summary: A python project aimed at extracting embeddings from textual data and performing semantic search. This version supports only the basic onnx model, no bge-m3 or e5 models.
Author: Carlo Moro
Author-email: Carlo Moro <cnmoro@gmail.com>
Project-URL: Homepage, https://github.com/cnmoro/Mini-Vector-DB
Project-URL: Bug Tracker, https://github.com/cnmoro/Mini-Vector-DB/issues
Classifier: Programming Language :: Python :: 3
Classifier: License :: OSI Approved :: MIT License
Classifier: Operating System :: OS Independent
Requires-Python: >=3.7
License-File: LICENSE
Requires-Dist: numpy
Requires-Dist: faiss-cpu
Requires-Dist: pytest
Requires-Dist: pytest-cov
Requires-Dist: scikit-learn
Requires-Dist: thefuzz[speedup]
Requires-Dist: onnxruntime
Requires-Dist: onnxruntime-extensions
Requires-Dist: usearch
Dynamic: author
Dynamic: license-file
Dynamic: requires-python
